snake/__init__.py
snake/__main__.py
snake/app.py
snakesnake-0.0.1.dist-info/METADATA
snakesnake-0.0.1.dist-info/WHEEL
snakesnake-0.0.1.dist-info/entry_points.txt
snakesnake-0.0.1.dist-info/license.txt
snakesnake-0.0.1.dist-info/top_level.txt
snakesnake-0.0.1.dist-info/RECORD
